MANIFEST.in
README.markdown
repoman
setup.py
repoman_client/__init__.py
repoman_client/__version__.py
repoman_client/client.py
repoman_client/config.py
repoman_client/display.py
repoman_client/exceptions.py
repoman_client/imageutils.py
repoman_client/logger.py
repoman_client/parsers.py
repoman_client/subcommand.py
repoman_client/utils.py
repoman_client.egg-info/PKG-INFO
repoman_client.egg-info/SOURCES.txt
repoman_client.egg-info/dependency_links.txt
repoman_client.egg-info/not-zip-safe
repoman_client.egg-info/requires.txt
repoman_client.egg-info/top_level.txt
repoman_client/subcommands/__init__.py
repoman_client/subcommands/config.py
repoman_client/subcommands/create.py
repoman_client/subcommands/diagnostic.py
repoman_client/subcommands/group_membership.py
repoman_client/subcommands/help.py
repoman_client/subcommands/listing.py
repoman_client/subcommands/modify.py
repoman_client/subcommands/permissions.py
repoman_client/subcommands/remove.py
repoman_client/subcommands/save.py
repoman_client/subcommands/sharing.py
repoman_client/subcommands/skeleton.py
repoman_client/subcommands/up_down.py
repoman_client/subcommands/version.py