Metadata-Version: 1.0
Name: repoman-client
Version: 0.3.22
Summary: Client to connect to Repoman image repository.
Home-page: http://github.com/hep-gc/repoman
Author: Kyle Fransham, Drew Harris, Matthew Vliet
Author-email: fransham@uvic.ca, dbharris@uvic.ca, mvliet@uvic.ca
License: UNKNOWN
Platform: UNKNOWN
